README.md
setup.cfg
setup.py
xCore.py
xinabox_CORE.egg-info/PKG-INFO
xinabox_CORE.egg-info/SOURCES.txt
xinabox_CORE.egg-info/dependency_links.txt
xinabox_CORE.egg-info/top_level.txt