Metadata-Version: 2.1
Name: xinabox-CORE
Version: 0.0.8
Summary: I2C Core for CC03/CS11/CW03, CW02, CW01, Raspberry Pi and Microbit
Home-page: https://github.com/xinabox/Python-CORE
Author: Luqmaan Baboo
Author-email: luqmaanbaboo@gmail.com
License: UNKNOWN
Platform: UNKNOWN
Classifier: Programming Language :: Python :: 3
Classifier: License :: OSI Approved :: MIT License
Classifier: Operating System :: OS Independent
Requires-Python: >=3.6
